{
  "routes": [
    {
      "method": "GET",
      "path": "/main-posts",
      "handler": "main-post.find",
      "config": {
        "policies": []
      }
    },
    {
      "method": "GET",
      "path": "/main-posts/count",
      "handler": "main-post.count",
      "config": {
        "policies": []
      }
    },
    {
      "method": "GET",
      "path": "/main-posts/:id",
      "handler": "main-post.findOne",
      "config": {
        "policies": []
      }
    },
    {
      "method": "POST",
      "path": "/main-posts",
      "handler": "main-post.create",
      "config": {
        "policies": []
      }
    },
    {
      "method": "PUT",
      "path": "/main-posts/:id",
      "handler": "main-post.update",
      "config": {
        "policies": []
      }
    },
    {
      "method": "DELETE",
      "path": "/main-posts/:id",
      "handler": "main-post.delete",
      "config": {
        "policies": []
      }
    }
  ]
}
